SightDistance12D/__init__.py
SightDistance12D/capability.py
SightDistance12D/parameters.py
SightDistance12D-1.0.0.dist-info/METADATA
SightDistance12D-1.0.0.dist-info/WHEEL
SightDistance12D-1.0.0.dist-info/top_level.txt
SightDistance12D-1.0.0.dist-info/RECORD
