Metadata-Version: 2.1
Name: SightDistance12D
Version: 1.0.0
Summary: Functions for summerising 12D Sight Stopping Distance reports
Requires-Dist: numpy >=1.26.4
Requires-Dist: XlsxWriter >=3.2.0
Requires-Dist: tabulate >=0.9.0
Requires-Dist: beautifulsoup4 >=4.12.3
Requires-Dist: pandas >=2.2.2
Requires-Dist: matplotlib >=3.9.0
